th3n1c3l1b/__init__.py
th3n1c3l1b/broker_client.py
th3n1c3l1b/df_lib.py
th3n1c3l1b/lib.py
th3n1c3l1b-0.1.2.3.dist-info/METADATA
th3n1c3l1b-0.1.2.3.dist-info/WHEEL
th3n1c3l1b-0.1.2.3.dist-info/RECORD
